logutilities/__init__.py
logutilities/functions.py
logutilities-0.0.1.dist-info/METADATA
logutilities-0.0.1.dist-info/WHEEL
logutilities-0.0.1.dist-info/top_level.txt
logutilities-0.0.1.dist-info/RECORD
