Metadata-Version: 2.1
Name: logutilities
Version: 0.0.1
Summary: Utilities package for function logging
Home-page: https://github.com/AlexXTW/logging_utils
Author: Alex X.T. Wang
Author-email: xintong.wang@riotinto.com
License: UNKNOWN
Platform: UNKNOWN
Classifier: Programming Language :: Python :: 3
Classifier: License :: OSI Approved :: MIT License
Classifier: Operating System :: OS Independent
Requires-Python: >=3.6
